tlopack/__init__.py
tlopack/api.py
tlopack/cli.py
tlopack-0.1.0.dist-info/METADATA
tlopack-0.1.0.dist-info/WHEEL
tlopack-0.1.0.dist-info/entry_points.txt
tlopack-0.1.0.dist-info/RECORD
