Metadata-Version: 2.4
Name: tlopack
Version: 0.1.0
Summary: A CLI tool for TLO searches
Project-URL: Homepage, https://github.com/yourusername/tlopack
Author: TLOPack
Requires-Python: >=3.8
Requires-Dist: requests>=2.31.0
Requires-Dist: rich>=13.7.0
Requires-Dist: typer>=0.9.0
